RealitySix/__init__.py
RealitySix/setup.py
Reality_six-0.2.6.dist-info/METADATA
Reality_six-0.2.6.dist-info/WHEEL
Reality_six-0.2.6.dist-info/top_level.txt
Reality_six-0.2.6.dist-info/RECORD
