Metadata-Version: 2.1
Name: Reality-six
Version: 0.2.6
Summary: A simple package that tells you reality.
Home-page: https://github.com/Hillo232/Reality/tree/main
Author: pkg_uploaders
Author-email: example@example.com
License: UNKNOWN
Platform: UNKNOWN
Classifier: Programming Language :: Python :: 3
Classifier: License :: OSI Approved :: MIT License
Classifier: Operating System :: OS Independent
